LICENSE
README.md
setup.cfg
setup.py
src/resoncalc/__init__.py
src/resoncalc/detection.py
src/resoncalc/femdvr.py
src/resoncalc/graphics.py
src/resoncalc/input.py
src/resoncalc/output.py
src/resoncalc/potential.py
src/resoncalc.egg-info/PKG-INFO
src/resoncalc.egg-info/SOURCES.txt
src/resoncalc.egg-info/dependency_links.txt
src/resoncalc.egg-info/entry_points.txt
src/resoncalc.egg-info/not-zip-safe
src/resoncalc.egg-info/requires.txt
src/resoncalc.egg-info/top_level.txt