Metadata-Version: 2.1
Name: resoncalc
Version: 0.1.2
Summary: Calculate bound states and resonances for potential
Home-page: https://github.com/hydratk/resoncalc
Author: Petr Rasek
Author-email: petr.rasek.w@gmail.com
License: MIT
Keywords: resoncalc
Classifier: Development Status :: 2 - Pre-Alpha
Classifier: Intended Audience :: Developers
Classifier: License :: OSI Approved :: MIT License
Classifier: Natural Language :: English
Classifier: Programming Language :: Python :: 3
Classifier: Programming Language :: Python :: 3.11
License-File: LICENSE
Requires-Dist: numpy>=1.25.1
Requires-Dist: scipy>=1.11.1
Requires-Dist: sympy>=1.12
Requires-Dist: matplotlib>=3.7.2
